mail_devel/__init__.py
mail_devel/__main__.py
mail_devel/auth.py
mail_devel/builder.py
mail_devel/http.py
mail_devel/mailbox.py
mail_devel/service.py
mail_devel/smtp.py
mail_devel/utils.py
mail_devel/automation/__init__.py
mail_devel/automation/reply_always.py
mail_devel/automation/reply_once.py
mail_devel/resources/__init__.py
mail_devel/resources/index.html
mail_devel/resources/main.css
mail_devel/resources/main.js
mail_devel-0.16.0.dist-info/licenses/LICENSE
mail_devel-0.16.0.dist-info/METADATA
mail_devel-0.16.0.dist-info/WHEEL
mail_devel-0.16.0.dist-info/entry_points.txt
mail_devel-0.16.0.dist-info/top_level.txt
mail_devel-0.16.0.dist-info/RECORD
