Metadata-Version: 2.4
Name: mail-devel
Version: 0.16.0
Summary: IMAP and SMTP in memory test server
Home-page: https://github.com/fkantelberg/mail-devel
Author: Florian Kantelberg
Author-email: florian.kantelberg@mailbox.org
License: MIT
Keywords: imap smtp development
Classifier: License :: OSI Approved :: MIT License
Classifier: Operating System :: OS Independent
Classifier: Programming Language :: Python :: 3
Requires-Python: >=3.11
License-File: LICENSE
Requires-Dist: aiohttp-jinja2
Requires-Dist: aiosmtpd
Requires-Dist: pymap~=0.36
Requires-Dist: passlib
Requires-Dist: typing-extensions
Dynamic: license-file
